neurum_db/__init__.py
neurum_db/delete.py
neurum_db/get_cell.py
neurum_db/get_column.py
neurum_db/post.py
neurum_db/update.py
neurum_db-0.3.9.dist-info/LICENSE.txt
neurum_db-0.3.9.dist-info/METADATA
neurum_db-0.3.9.dist-info/WHEEL
neurum_db-0.3.9.dist-info/top_level.txt
neurum_db-0.3.9.dist-info/RECORD
