Metadata-Version: 2.1
Name: neurum-db
Version: 0.3.9
Summary: a simple powerful python database built on notion powered by Neurum.
Home-page: 
Author: Vansh Shah
Author-email: vanshshah836@gmail.com
Keywords: python notion database db free spreadsheet backend
Classifier: Development Status :: 2 - Pre-Alpha
Classifier: Intended Audience :: Developers
Classifier: Operating System :: MacOS :: MacOS X
Classifier: Operating System :: Microsoft :: Windows
Classifier: Operating System :: Unix
Classifier: License :: OSI Approved :: MIT License
Classifier: Programming Language :: Python
License-File: LICENSE.txt
